setup.cfg
setup.py
Products/__init__.py
Products/__init__.pyc
Products.ECGraphBox.egg-info/PKG-INFO
Products.ECGraphBox.egg-info/SOURCES.txt
Products.ECGraphBox.egg-info/dependency_links.txt
Products.ECGraphBox.egg-info/entry_points.txt
Products.ECGraphBox.egg-info/namespace_packages.txt
Products.ECGraphBox.egg-info/not-zip-safe
Products.ECGraphBox.egg-info/requires.txt
Products.ECGraphBox.egg-info/top_level.txt
Products/ECGraphBox/CHANGES.txt
Products/ECGraphBox/LICENSE.GPL
Products/ECGraphBox/LICENSE.TXT
Products/ECGraphBox/README.txt
Products/ECGraphBox/TODO.txt
Products/ECGraphBox/__init__.py
Products/ECGraphBox/config.py
Products/ECGraphBox/configure.zcml
Products/ECGraphBox/make_i18n.bat
Products/ECGraphBox/profiles.zcml
Products/ECGraphBox/refresh.txt
Products/ECGraphBox/setuphandlers.py
Products/ECGraphBox/version.txt
Products/ECGraphBox/content/ECGraph.py
Products/ECGraphBox/content/ECGraphBox.py
Products/ECGraphBox/content/__init__.py
Products/ECGraphBox/content/interfaces.py
Products/ECGraphBox/i18n/eduComponents-de.po
Products/ECGraphBox/i18n/eduComponents.pot
Products/ECGraphBox/i18n/plone-de.po
Products/ECGraphBox/i18n/schemas.pot
Products/ECGraphBox/profiles/default/ECGraphBox_marker.txt
Products/ECGraphBox/profiles/default/cssregistry.xml
Products/ECGraphBox/profiles/default/factorytool.xml
Products/ECGraphBox/profiles/default/import_steps.xml
Products/ECGraphBox/profiles/default/jsregistry.xml
Products/ECGraphBox/profiles/default/metadata.xml
Products/ECGraphBox/profiles/default/skins.xml
Products/ECGraphBox/profiles/default/types.xml
Products/ECGraphBox/profiles/default/workflows.xml
Products/ECGraphBox/profiles/default/types/ECGraph.xml
Products/ECGraphBox/profiles/default/types/ECGraphBox.xml
Products/ECGraphBox/skins/ecgraphbox_images/ec_accept.png
Products/ECGraphBox/skins/ecgraphbox_images/ec_error.png
Products/ECGraphBox/skins/ecgraphbox_images/ec_exclamation.png
Products/ECGraphBox/skins/ecgraphbox_images/ec_tool.png
Products/ECGraphBox/skins/ecgraphbox_images/eca.png
Products/ECGraphBox/skins/ecgraphbox_images/ecaab.png
Products/ECGraphBox/skins/ecgraphbox_images/ecaab.png.metadata
Products/ECGraphBox/skins/ecgraphbox_images/ecaat.png
Products/ECGraphBox/skins/ecgraphbox_styles/README.txt
Products/ECGraphBox/skins/ecgraphbox_styles/ecg_style.css
