Metadata-Version: 1.0
Name: Products.ECGraphBox
Version: 1.4.0
Summary: ECGraphBox is a product especially designed for graph assignments.
Home-page: http://plone.org/products/ecgraphbox/
Author: Gino Gulamhussene and Fabian Fett
Author-email: ginogulamhussene@gmx.de and fett@st.ovgu.de
License: GPL
Platform: UNKNOWN
Classifier: Framework :: Plone
Classifier: Framework :: Zope2
Classifier: Programming Language :: Python
Classifier: Topic :: Software Development :: Libraries :: Python Modules
